ocr_layout/__init__.py
ocr_layout/formatter.py
ocr_layout_formatter-0.1.1.dist-info/METADATA
ocr_layout_formatter-0.1.1.dist-info/WHEEL
ocr_layout_formatter-0.1.1.dist-info/top_level.txt
ocr_layout_formatter-0.1.1.dist-info/RECORD
