Metadata-Version: 2.4
Name: ocr-layout-formatter
Version: 0.1.1
Summary: Convert OCR JSON to spatial text preserving document layout
Author-email: datasci_tree3 <datasci@promes.co.th>
Project-URL: Homepage, https://gitlab.com/promes-in-th/products/fuse/ocr-layout
Classifier: Programming Language :: Python :: 3
Classifier: License :: OSI Approved :: MIT License
Classifier: Operating System :: OS Independent
Requires-Python: >=3.8
